README.md
setup.py
logicmonitor_sdk/__init__.py
logicmonitor_sdk/api_client.py
logicmonitor_sdk/configuration.py
logicmonitor_sdk/rest.py
logicmonitor_sdk.egg-info/PKG-INFO
logicmonitor_sdk.egg-info/SOURCES.txt
logicmonitor_sdk.egg-info/dependency_links.txt
logicmonitor_sdk.egg-info/requires.txt
logicmonitor_sdk.egg-info/top_level.txt
logicmonitor_sdk/api/__init__.py
logicmonitor_sdk/api/lm_api.py
logicmonitor_sdk/models/__init__.py
logicmonitor_sdk/models/access_group.py
logicmonitor_sdk/models/access_group_pagination_response.py
logicmonitor_sdk/models/access_log_pagination_response.py
logicmonitor_sdk/models/ack_collector_down.py
logicmonitor_sdk/models/admin.py
logicmonitor_sdk/models/admin_pagination_response.py
logicmonitor_sdk/models/advanced_field_filter.py
logicmonitor_sdk/models/advanced_metrics_graph_info.py
logicmonitor_sdk/models/aggregate_collector_attribute.py
logicmonitor_sdk/models/alert.py
logicmonitor_sdk/models/alert_ack.py
logicmonitor_sdk/models/alert_filters.py
logicmonitor_sdk/models/alert_forecasting_report.py
logicmonitor_sdk/models/alert_list_pagination_response.py
logicmonitor_sdk/models/alert_pagination_response.py
logicmonitor_sdk/models/alert_report.py
logicmonitor_sdk/models/alert_response.py
logicmonitor_sdk/models/alert_rule.py
logicmonitor_sdk/models/alert_rule_pagination_response.py
logicmonitor_sdk/models/alert_sla_report.py
logicmonitor_sdk/models/alert_threshold_report.py
logicmonitor_sdk/models/alert_trends_metric.py
logicmonitor_sdk/models/alert_trends_report.py
logicmonitor_sdk/models/alert_widget.py
logicmonitor_sdk/models/alert_widget_data.py
logicmonitor_sdk/models/alerts_health_check_report.py
logicmonitor_sdk/models/api_perf_metrics.py
logicmonitor_sdk/models/api_token.py
logicmonitor_sdk/models/api_token_pagination_response.py
logicmonitor_sdk/models/applies_to_function.py
logicmonitor_sdk/models/array_node.py
logicmonitor_sdk/models/aruba_central_collector_attribute.py
logicmonitor_sdk/models/aruba_central_iap_interface_discovery_method.py
logicmonitor_sdk/models/aruba_central_iap_network_discovery_method.py
logicmonitor_sdk/models/aruba_central_iap_radio_discovery_method.py
logicmonitor_sdk/models/assignment.py
