Metadata-Version: 1.0
Name: logicmonitor-sdk
Version: 3.0.230
Summary: LogicMonitor REST API
Home-page: https://github.com/logicmonitor/lm-sdk-python
Author: UNKNOWN
Author-email: UNKNOWN
License: UNKNOWN
Keywords: Swagger,LogicMonitor REST API
Platform: UNKNOWN
